py_hydroweb/__init__.py
py_hydroweb/client.py
py_hydroweb/collection.py
py_hydroweb/download_basket.py
py_hydroweb/download_info.py
py_hydroweb/exceptions.py
py_hydroweb-1.1.0.dist-info/LICENSE
py_hydroweb-1.1.0.dist-info/METADATA
py_hydroweb-1.1.0.dist-info/WHEEL
py_hydroweb-1.1.0.dist-info/top_level.txt
py_hydroweb-1.1.0.dist-info/RECORD
