Metadata-Version: 2.1
Name: py-hydroweb
Version: 1.1.0
Summary: Python API to search and download hydrological data from the hydroweb.next catalog
Author-email: "hydroweb.next operational team" <exp.hysope2@cnes.fr>
Maintainer-email: "hydroweb.next operational team" <exp.hysope2@cnes.fr>
License: Apache 2.0
Project-URL: Home, https://github.com/CNES/py-hydroweb
Project-URL: HydrowebNext, https://hydroweb.next.theia-land.fr
Project-URL: Source, https://github.com/CNES/py-hydroweb
Keywords: hydroweb,water,hydrology,inland water,coastal,scientific data,search,download,catalog,cnes,dataterra,theia
Classifier: Intended Audience :: Science/Research
Classifier: Intended Audience :: Developers
Classifier: Intended Audience :: End Users/Desktop
Classifier: Programming Language :: Python :: 3
Classifier: Programming Language :: Python :: 3 :: Only
Classifier: Programming Language :: Python :: 3.8
Classifier: Programming Language :: Python :: 3.9
Classifier: Programming Language :: Python :: 3.10
Classifier: Programming Language :: Python :: 3.11
Classifier: Programming Language :: Python :: 3.12
Classifier: Programming Language :: Python :: 3.13
Classifier: License :: OSI Approved :: Apache Software License
Classifier: Operating System :: OS Independent
Requires-Python: >=3.8
License-File: LICENSE
Requires-Dist: requests ~=2.32.3
Requires-Dist: retry2 ~=0.9.5
Requires-Dist: tqdm ~=4.66.5
Provides-Extra: dev
Requires-Dist: coverage ==7.0.* ; extra == 'dev'
Requires-Dist: black ==22.12.* ; extra == 'dev'
Requires-Dist: flake8 ==5.0.* ; extra == 'dev'
Requires-Dist: flake8-annotations ==2.9.* ; extra == 'dev'
Requires-Dist: flake8-bandit ==4.1.* ; extra == 'dev'
Requires-Dist: flake8-bugbear ==23.1.* ; extra == 'dev'
Requires-Dist: flake8-eradicate ==1.4.* ; extra == 'dev'
Requires-Dist: flake8-quotes ==3.3.* ; extra == 'dev'
Requires-Dist: flake8-use-fstring ==1.4 ; extra == 'dev'
Requires-Dist: isort ==5.11.* ; extra == 'dev'
Requires-Dist: pylint ==2.15.* ; extra == 'dev'
Requires-Dist: pylint-sonarjson ==1.0.* ; extra == 'dev'
Requires-Dist: pytest ==7.2.* ; extra == 'dev'
Requires-Dist: pytest-cov ==4.0.* ; extra == 'dev'
Requires-Dist: pytest-html ==3.2.* ; extra == 'dev'
Requires-Dist: pytest-mock ==3.10.* ; extra == 'dev'
Requires-Dist: cnes-pylint-extension ==6.0.0 ; extra == 'dev'
